store.py
store_cli-1.0.0.dist-info/DESCRIPTION.rst
store_cli-1.0.0.dist-info/METADATA
store_cli-1.0.0.dist-info/RECORD
store_cli-1.0.0.dist-info/WHEEL
store_cli-1.0.0.dist-info/entry_points.txt
store_cli-1.0.0.dist-info/metadata.json
store_cli-1.0.0.dist-info/top_level.txt
