Metadata-Version: 2.0
Name: store-cli
Version: 1.0.0
Summary: A Tool to save commands used in terminal and create a backup on Google drive
Home-page: https://github.com/iyanuashiri/store
Author: Iyanu Ajao
Author-email: ajaoiyanu@gmail.com
License: MIT
Platform: UNKNOWN
Classifier: License :: OSI Approved :: MIT License
Classifier: Programming Language :: Python
Classifier: Programming Language :: Python :: 3
Classifier: Programming Language :: Python :: 3.6
Classifier: Programming Language :: Python :: Implementation :: CPython
Classifier: Programming Language :: Python :: Implementation :: PyPy
Requires-Python: >=3.6.0
Requires-Dist: click
Requires-Dist: google-api-python-client
Requires-Dist: terminaltables
Requires-Dist: oauth2client
